topsis_102203872/__init__.py
topsis_102203872/topsis_102203872.py
topsis_102203872-0.1.0.dist-info/LICENSE.txt
topsis_102203872-0.1.0.dist-info/METADATA
topsis_102203872-0.1.0.dist-info/WHEEL
topsis_102203872-0.1.0.dist-info/entry_points.txt
topsis_102203872-0.1.0.dist-info/top_level.txt
topsis_102203872-0.1.0.dist-info/RECORD
