Metadata-Version: 2.2
Name: topsis_102203872
Version: 0.1.0
Summary: TOPSIS Algorithm Implementation with CLI
Home-page: https://github.com/arpitaggarwal/topsis_package
Author: Arpit Aggarwal
Author-email: your_email@example.com
Classifier: Programming Language :: Python :: 3
Classifier: License :: OSI Approved :: MIT License
Classifier: Operating System :: OS Independent
Requires-Python: >=3.6
License-File: LICENSE.txt
Requires-Dist: numpy
Requires-Dist: pandas
Requires-Dist: openpyxl
Dynamic: author
Dynamic: author-email
Dynamic: classifier
Dynamic: description
Dynamic: description-content-type
Dynamic: home-page
Dynamic: requires-dist
Dynamic: requires-python
Dynamic: summary
